torchmorph/__init__.py
torchmorph/affine_mapping.py
torchmorph/constant.py
torchmorph/derivative.py
torchmorph/factory.py
torchmorph/interface.py
torchmorph/mask.py
torchmorph/py.typed
torchmorph/tensor_like.py
torchmorph/util.py
torchmorph/visualization.py
torchmorph/affine_transformation/__init__.py
torchmorph/affine_transformation/affine_transformation.py
torchmorph/affine_transformation/diagonal_matrix.py
torchmorph/affine_transformation/matrix.py
torchmorph/composable_mapping/__init__.py
torchmorph/composable_mapping/composable_mapping.py
torchmorph/composable_mapping/interface.py
torchmorph/composable_mapping/util.py
torchmorph/coordinate_system/__init__.py
torchmorph/coordinate_system/coordinate_system.py
torchmorph/coordinate_system/coordinate_system_factory.py
torchmorph/coordinate_system/reformatting_reference.py
torchmorph/coordinate_system/reformatting_spatial_shape.py
torchmorph/mappable_tensor/__init__.py
torchmorph/mappable_tensor/grid.py
torchmorph/mappable_tensor/mappable_tensor.py
torchmorph/mappable_tensor/util.py
torchmorph/sampler/__init__.py
torchmorph/sampler/b_spline.py
torchmorph/sampler/convolution_sampling.py
torchmorph/sampler/default.py
torchmorph/sampler/gaussian.py
torchmorph/sampler/interface.py
torchmorph/sampler/interpolate.py
torchmorph/sampler/interpolator.py
torchmorph/sampler/inverse.py
torchmorph/sampler/sampling_cache.py
torchmorph/sampler/scaling_and_squaring.py
torchmorph/sampler/separable_sampler.py
torchmorph/sampler/_second_order_differentiable_grid_sample/__init__.py
torchmorph/sampler/_second_order_differentiable_grid_sample/cuda_gridsample.py
torchmorph/sampler/_second_order_differentiable_grid_sample/grid_sample.py
torchmorph/sampler/_second_order_differentiable_grid_sample/gridsample_cuda.cpp
torchmorph/sampler/_second_order_differentiable_grid_sample/gridsample_cuda.cu
torchmorph/sampler/_second_order_differentiable_grid_sample/naive_gridsample.py
torchmorph-0.1.6.dist-info/licenses/LICENSE
torchmorph-0.1.6.dist-info/METADATA
torchmorph-0.1.6.dist-info/WHEEL
torchmorph-0.1.6.dist-info/top_level.txt
torchmorph-0.1.6.dist-info/RECORD
